macros/__init__.py
mkdocs_duon-0.1.0.dist-info/licenses/LICENSE.md
theme/__init__.py
theme/base.html
theme/highlight.min.js
theme/logo.svg
theme/main.html
theme/mkdocs_theme.yml
theme/nav.html
theme/search.html
theme/styles.css
theme/fonts/pt-serif-v17-latin-regular.woff
theme/fonts/pt-serif-v17-latin-regular.woff2
mkdocs_duon-0.1.0.dist-info/METADATA
mkdocs_duon-0.1.0.dist-info/WHEEL
mkdocs_duon-0.1.0.dist-info/entry_points.txt
mkdocs_duon-0.1.0.dist-info/top_level.txt
mkdocs_duon-0.1.0.dist-info/RECORD
