Metadata-Version: 2.4
Name: mkdocs-duon
Version: 0.1.0
Summary: Default mkdocs theme for Duon projects
Home-page: https://github.com/duoncode/mkdocs-theme
Author: ebene fünf GmbH
Author-email: duon@ebenefuenf.de
License: MIT
License-File: LICENSE.md
Requires-Dist: mkdocs>=1.6
Requires-Dist: mkdocs-macros-plugin>=0.7
Requires-Dist: pymdown-extensions>=10.3
Dynamic: author
Dynamic: author-email
Dynamic: description
Dynamic: description-content-type
Dynamic: home-page
Dynamic: license
Dynamic: license-file
Dynamic: requires-dist
Dynamic: summary
